CHANGELOG.md
initial/__init__.py
initial/data/__init__.py
initial/data/flatland.txt
initial/datasets.py
initial/hellow.py
initial/initial.py
initial/plotting.py
tests/einstein.txt
tests/test_initial.py
initial-0.2.2.dist-info/LICENSE
initial-0.2.2.dist-info/METADATA
initial-0.2.2.dist-info/WHEEL
initial-0.2.2.dist-info/RECORD
