Metadata-Version: 2.1
Name: initial
Version: 0.2.2
Summary: For testing ws python package.
License: MIT
Author: Ming
Requires-Python: >=3.9,<4.0
Classifier: License :: OSI Approved :: MIT License
Classifier: Programming Language :: Python :: 3
Classifier: Programming Language :: Python :: 3.9
Classifier: Programming Language :: Python :: 3.10
Classifier: Programming Language :: Python :: 3.11
Requires-Dist: matplotlib (>=3.7.2)
Requires-Dist: numpy (==1.21.5) ; python_version >= "3.7" and python_version < "3.11"
